my_package/__init__.py
my_package/calc.py
my_package_tomergabay-0.1.0.dist-info/LICENSE
my_package_tomergabay-0.1.0.dist-info/WHEEL
my_package_tomergabay-0.1.0.dist-info/METADATA
my_package_tomergabay-0.1.0.dist-info/RECORD
