Metadata-Version: 2.1
Name: my-package-tomergabay
Version: 0.1.0
Summary: Template for a professional (open source) Python package.
Author: Tomer Gabay
Author-email: tomergabay001@gmail.com
Requires-Python: >=3.10,<4.0
Classifier: Programming Language :: Python :: 3
Classifier: Programming Language :: Python :: 3.10
